tcfnetworks/__init__.py
tcfnetworks/annotators/__init__.py
tcfnetworks/annotators/base.py
tcfnetworks/annotators/cooccurrence.py
tcfnetworks/annotators/dependency.py
tcfnetworks/exporters/__init__.py
tcfnetworks/exporters/d3_html.py
tcfnetworks/exporters/d3_json.py
tcfnetworks/exporters/graphml.py
tcfnetworks/exporters/data/d3.html
tcfnetworks/exporters/data/d3.v3.min.js
tcfnetworks/exporters/data/tcf2graphml.xsl
TCFnetworks-0.3.0.dist-info/COPYING
TCFnetworks-0.3.0.dist-info/METADATA
TCFnetworks-0.3.0.dist-info/WHEEL
TCFnetworks-0.3.0.dist-info/pbr.json
TCFnetworks-0.3.0.dist-info/top_level.txt
TCFnetworks-0.3.0.dist-info/RECORD
