Metadata-Version: 2.1
Name: TCFnetworks
Version: 0.3.0
Summary: Python TCF network services
Home-page: https://github.com/SeNeReKo/TCFnetworks
Author: Frederik Elwert
Author-email: frederik.elwert@web.de
License-File: COPYING
